ploomy/__init__.py
ploomy/bloom_filter.py
ploomy/exceptions.py
ploomy/operation/__init__.py
ploomy/operation/check.py
ploomy/operation/create.py
ploomy/operation/drop.py
ploomy/operation/flush.py
ploomy/operation/info.py
ploomy/operation/list.py
ploomy/operation/operation.py
ploomy/operation/set_.py
ploomy-0.1.dist-info/LICENSE
ploomy-0.1.dist-info/METADATA
ploomy-0.1.dist-info/WHEEL
ploomy-0.1.dist-info/top_level.txt
ploomy-0.1.dist-info/RECORD
